setup.py
jsontools/__init__.py
jsontools/cmp.py
jsontools/diff.py
jsontools/fuzz.py
jsontools.egg-info/PKG-INFO
jsontools.egg-info/SOURCES.txt
jsontools.egg-info/dependency_links.txt
jsontools.egg-info/top_level.txt
jsontools.egg-info/zip-safe
test/cmp_test.py
test/diff_test.py
