Metadata-Version: 1.1
Name: jsontools
Version: 0.1
Summary: jsontools - Useful utilities for JSON
Home-page: http://www.davispj.com/svn/projects/jsontools
Author: Paul Joseph Davis
Author-email: paul.joseph.davis@gmail.com
License: MIT
Platform: any
Classifier: Development Status :: 3 - Alpha
Classifier: Intended Audience :: Developers
Classifier: License :: OSI Approved :: MIT License
Classifier: Operating System :: OS Independent
Classifier: Programming Language :: Python
Classifier: Topic :: Software Development :: Libraries :: Python Modules
Requires: simplejson
